{
  "subAreas": {
    "neck-upper-trapezius": {
      "name": "טרפז עליון",
      "description": "חלק עליון של הכתפיים, ליד בסיס הצוואר"
    },
    "neck-levator-scapulae": {
      "name": "מרים השכמה",
      "description": "צד הצוואר, מהצוואר העליון אל הקצה הפנימי של עצם השכמה"
    },
    "neck-cervical-paraspinals": {
      "name": "צוואר אחורי ותת-עורף",
      "description": "חלקו האחורי של הצוואר ובסיס הגולגולת"
    },
    "shoulders-rotator-cuff": {
      "name": "שרוול המסובבים"
    },
    "shoulders-deltoid": {
      "name": "דלתואיד"
    },
    "shoulders-scapular-stabilizers": {
      "name": "מייצבי השכמה"
    },
    "shoulders-biceps-tendon": {
      "name": "גיד הראש הארוך של הביצפס"
    },
    "back-interscapular": {
      "name": "גב עליון (בין השכמות)"
    },
    "back-mid-thoracic": {
      "name": "אמצע הגב (עמוד שדרה חזי)"
    },
    "back-lumbar": {
      "name": "גב תחתון"
    },
    "wrist-flexor": {
      "name": "שורש כף יד (צד הכף) / תעלה קרפלית"
    },
    "wrist-extensor": {
      "name": "שורש כף יד (גב כף היד)"
    },
    "elbow-lateral": {
      "name": "מרפק חיצוני (מרפק טניס)"
    },
    "elbow-medial": {
      "name": "מרפק פנימי (מרפק גולפר)"
    },
    "wrist-de-quervains": {
      "name": "דלקת גידי דה קוורן"
    },
    "hip-glutes-medius": {
      "name": "שריר העכוז האמצעי"
    },
    "hip-glutes-maximus": {
      "name": "שריר העכוז הגדול"
    },
    "knees-patellofemoral": {
      "name": "מפרק הפיקה-ירך"
    },
    "knees-hamstring": {
      "name": "שרירי הירך האחוריים (המסטרינג)"
    },
    "foot-ankle-achilles": {
      "name": "גיד אכילס"
    },
    "foot-ankle-plantar": {
      "name": "פאשיה פלנטרית"
    },
    "foot-ankle-lateral": {
      "name": "קרסול חיצוני"
    }
  },
  "exercises": {
    "ex-band-shrug": {
      "name": "משיכת כתפיים עם גומיה",
      "targetMuscles": "טרפז עליון, מרים השכמה",
      "mechanism": "מחזק את הטרפז העליון בטווח תנועה מלא, ומאזן הפעלה טוניציטית כרונית הנובעת מישיבה ממושכת. אנדרסן ואח' הראו שאימון התנגדות מפחית כאבי טרפז עליון.",
      "instructions": [
        "עמוד/י על אמצע גומיה ארוכה, רגליים ברוחב אגן.",
        "אחז/י את הקצוות בצדדים, זרועות ישרות, כפות הידיים פונות פנימה.",
        "ללא כיפוף מרפקים, הרם/י את שתי הכתפיים ישר כלפי מעלה לכיוון האוזניים.",
        "השהה/י שניה אחת בנקודה העליונה.",
        "הורד/י בשליטה במשך 2 שניות."
      ],
      "tempo": "2-1-2",
      "bandTensionNote": "התחל/י באדום, התקדם/י לירוק או כחול ככל ש-12 חזרות הופכות לקלות.",
      "frequency": "3-5 ימים בשבוע",
      "commonMistakes": [
        "סיבוב כתפיים (זוהי הרמה אנכית בלבד)",
        "הוצאת הסנטר קדימה",
        "עצירת נשימה"
      ],
      "contraindications": [
        "רדיקולופתיה צווארית חריפה עם נימול בזרוע",
        "צליפת שוט לאחרונה (פחות משבועיים)",
        "יתר לחץ דם לא מאוזן"
      ],
      "beginnerModification": "משיכת כתפיים במשקל גוף (ללא גומיה) ב-1-2 השבועות הראשונים, או משיכת כתפיים בישיבה עם גומיה צהובה.",
      "evidenceSummary": "מחקר אקראי מבוקר של 198 עובדי משרד עם כאבי צוואר/כתף תכופים. רק 2 דקות ביום של תרגילי גומיה אלסטית, 5 ימים בשבוע למשך 10 שבועות, הפחיתו כאב באופן משמעותי בהשוואה לקבוצת הביקורת."
    },
    "ex-levator-stretch": {
      "name": "מתיחת מרים השכמה עם גומיה",
      "targetMuscles": "מרים השכמה (התארכות פסיבית) ומורידי השכמה (פעיל)",
      "mechanism": "תנוחת ראש קדמית יוצרת הפעלת-יתר מתמשכת של מרים השכמה. עיגון השכמה בהורדה באמצעות הגומיה מאפשר התארכות אמיתית של השריר במקום הרמה מפצה של השכמה.",
      "instructions": [
        "שב/י זקוף ודרוך/י על גומיה עם כף הרגל השמאלית.",
        "אחז/י את הגומיה ביד שמאל בצד, זרוע ארוכה — זה מוריד את השכמה השמאלית.",
        "סובב/י את הראש 45 מעלות ימינה (הסתכל/י לכיוון בית השחי הימני).",
        "כווץ/י קלות את הסנטר פנימה.",
        "הנח/י את יד ימין על גב הראש והפעל/י סיוע קל כלפי מטה.",
        "החזק/י 30 שניות, חזור/חזרי 2-3 פעמים, ואז החלף/י צד."
      ],
      "tempo": "החזקה סטטית",
      "bandTensionNote": "צהוב או אדום — אור מספיק; הגומיה מעגנת, לא מעמיסה",
      "frequency": "2-3 פעמים ביום",
      "commonMistakes": [
        "הרמת השכמה (משבית את המתיחה)",
        "סיבוב הראש במקום כיפוף הצידה",
        "משיכה אגרסיבית מדי עם היד"
      ],
      "contraindications": [
        "רדיקולופתיה צווארית חריפה",
        "אי-יציבות צווארית בולטת",
        "סחרחורת הקשורה בתנועות צוואר"
      ],
      "beginnerModification": "ללא גומיה — פשוט שמור/י את היד למטה בצד ובצע/י את המתיחה.",
      "evidenceSummary": "מחקרים על תנוחת ראש קדמית ומרים השכמה הראו שעיגון השכמה בהורדה משפר את יעילות המתיחה ומפחית הפעלת-יתר ארוכת-טווח."
    },
    "ex-chin-tuck-band": {
      "name": "כניסת סנטר עם גומיה",
      "targetMuscles": "כופפי צוואר עמוקים (לונגוס קולי, לונגוס קפיטיס)",
      "mechanism": "אנשים עם כאבי צוואר כרוניים מראים פעילות מופחתת של כופפי הצוואר העמוקים (DCF) ושימוש-יתר מפצה של הכופפים השטחיים. חיזוק ה-DCF משפר תיאום נוירומוסקולרי, תנוחת ראש וכאב.",
      "instructions": [
        "שב/י או עמוד/י זקוף.",
        "כרוך/כרכי גומיה ארוכה מאחורי הצוואר העליון/עורף.",
        "אחז/י את שני הקצוות מלפנים בגובה החזה, זרועות קדימה ב-90 מעלות לעיגון.",
        "ללא הטיה, משוך/משכי את הסנטר ישר אחורה ('סנטר כפול') — החלקה אופקית.",
        "החזק/י 5 שניות.",
        "שחרר/י לאט."
      ],
      "tempo": "2-5-2 (עם החזקה איזומטרית של 5 שניות)",
      "bandTensionNote": "צהוב או אדום בלבד — עומסים כבדים יותר גורמים לגיוס של כופפים שטחיים",
      "frequency": "מדי יום",
      "commonMistakes": [
        "הנהון של הראש כלפי מטה — צריכה להיות תנועה אופקית",
        "הוצאת הסנטר קדימה בעת השחרור",
        "שימוש בגומיה כבדה"
      ],
      "contraindications": [
        "ניתוח צוואר לאחרונה",
        "דלקת מפרקים שגרונית עם אי-יציבות אטלנטו-אקסיאלית",
        "היצרות עמוד שדרה חמורה עם סימני מיאלופתיה"
      ],
      "beginnerModification": "כניסת סנטר בשכיבה על הגב על הרצפה ללא גומיה — כוח המשיכה מספק התנגדות מספקת.",
      "evidenceSummary": "אימון ממוקד של כופפי צוואר עמוקים שיפר דפוסי הפעלה שרירית והפחית כאב במטופלים עם כאבי צוואר כרוניים בהשוואה לאימון כללי."
    },
    "ex-band-external-rotation": {
      "name": "סיבוב כתף חיצוני עם גומיה"
    },
    "ex-lateral-raise": {
      "name": "הרמה צידית עם גומיה"
    },
    "ex-face-pull": {
      "name": "משיכת פנים עם גומיה"
    },
    "ex-banded-biceps-eccentric": {
      "name": "כפיפת מרפק עם גומיה ודגש אקסצנטרי"
    },
    "ex-seated-row": {
      "name": "חתירה בישיבה עם גומיה"
    },
    "ex-ytw": {
      "name": "תרגיל Y-T-W עם גומיה"
    },
    "ex-good-morning": {
      "name": "ציר ירך עם גומיה (Good Morning)"
    },
    "ex-median-nerve-glide": {
      "name": "החלקת עצב מדיאני"
    },
    "ex-wrist-extension": {
      "name": "יישור שורש כף יד עם גומיה"
    },
    "ex-tyler-twist": {
      "name": "סיבוב טיילר (יישור שורש כף יד אקסצנטרי)"
    },
    "ex-reverse-tyler": {
      "name": "סיבוב טיילר הפוך"
    },
    "ex-banded-thumb-eccentric": {
      "name": "יישור אגודל אקסצנטרי עם גומיה"
    },
    "ex-banded-clamshell": {
      "name": "תרגיל צדפה עם גומיה"
    },
    "ex-banded-glute-bridge": {
      "name": "גשר ישבן עם גומיה"
    },
    "ex-banded-tke": {
      "name": "יישור ברך סופי עם גומיה"
    },
    "ex-banded-hamstring-curl": {
      "name": "כפיפת ירך עם גומיה"
    },
    "ex-eccentric-heel-drop": {
      "name": "הורדת עקב אקסצנטרית"
    },
    "ex-plantar-fascia-stretch": {
      "name": "מתיחת פאשיה פלנטרית"
    },
    "ex-banded-eversion": {
      "name": "היפוך קרסול עם גומיה"
    }
  }
}
